pytkdocs-0.16.4.dist-info/METADATA
pytkdocs-0.16.4.dist-info/WHEEL
pytkdocs-0.16.4.dist-info/entry_points.txt
pytkdocs-0.16.4.dist-info/licenses/LICENSE
pytkdocs/__init__.py
pytkdocs/__main__.py
pytkdocs/cli.py
pytkdocs/debug.py
pytkdocs/loader.py
pytkdocs/objects.py
pytkdocs/parsers/__init__.py
pytkdocs/parsers/attributes.py
pytkdocs/parsers/docstrings/__init__.py
pytkdocs/parsers/docstrings/base.py
pytkdocs/parsers/docstrings/google.py
pytkdocs/parsers/docstrings/markdown.py
pytkdocs/parsers/docstrings/numpy.py
pytkdocs/parsers/docstrings/restructured_text.py
pytkdocs/properties.py
pytkdocs/py.typed
pytkdocs/serializer.py
pytkdocs-0.16.4.dist-info/RECORD
