Metadata-Version: 2.4
Name: pytkdocs
Version: 0.16.4
Summary: Load Python objects documentation.
Keywords: python,source,signature,docs
Author-Email: =?utf-8?q?Timoth=C3=A9e_Mazzucotelli?= <dev@pawamoy.fr>
License-Expression: ISC
License-File: LICENSE
Classifier: Development Status :: 4 - Beta
Classifier: Intended Audience :: Developers
Classifier: Programming Language :: Python
Classifier: Programming Language :: Python :: 3
Classifier: Programming Language :: Python :: 3 :: Only
Classifier: Programming Language :: Python :: 3.9
Classifier: Programming Language :: Python :: 3.10
Classifier: Programming Language :: Python :: 3.11
Classifier: Programming Language :: Python :: 3.12
Classifier: Programming Language :: Python :: 3.13
Classifier: Programming Language :: Python :: 3.14
Classifier: Topic :: Documentation
Classifier: Topic :: Software Development
Classifier: Topic :: Utilities
Classifier: Typing :: Typed
Project-URL: Homepage, https://mkdocstrings.github.io/pytkdocs
Project-URL: Documentation, https://mkdocstrings.github.io/pytkdocs
Project-URL: Changelog, https://mkdocstrings.github.io/pytkdocs/changelog
Project-URL: Repository, https://github.com/mkdocstrings/pytkdocs
Project-URL: Issues, https://github.com/mkdocstrings/pytkdocs/issues
Project-URL: Discussions, https://github.com/mkdocstrings/pytkdocs/discussions
Project-URL: Gitter, https://gitter.im/mkdocstrings/pytkdocs
Project-URL: Funding, https://github.com/sponsors/pawamoy
Requires-Python: >=3.9
Requires-Dist: astunparse>=1.6; python_version < "3.9"
Requires-Dist: cached-property>=1.5; python_version < "3.8"
Requires-Dist: typing-extensions>=3.7; python_version < "3.8"
Provides-Extra: numpy-style
Requires-Dist: docstring_parser>=0.7; extra == "numpy-style"
